mwatershed-0.5.4.dist-info/METADATA
mwatershed-0.5.4.dist-info/WHEEL
mwatershed-0.5.4.dist-info/licenses/AUTHORS.rst
mwatershed-0.5.4.dist-info/licenses/LICENSE
mwatershed/__init__.py
mwatershed/mwatershed.cp314-win_amd64.pyd
mwatershed-0.5.4.dist-info/RECORD
