Metadata-Version: 2.4
Name: mwatershed
Version: 0.5.4
Classifier: Development Status :: 2 - Pre-Alpha
Classifier: Intended Audience :: Developers
Classifier: License :: OSI Approved :: MIT License
Classifier: Natural Language :: English
Classifier: Programming Language :: Python :: 3.11
Classifier: Programming Language :: Python :: 3.12
Classifier: Programming Language :: Python :: 3.13
Requires-Dist: numpy>=1.18.0
Requires-Dist: bump-my-version>=1.1.2 ; extra == 'dev'
Requires-Dist: maturin>=1.9 ; extra == 'dev'
Requires-Dist: pytest>=8.3.3 ; extra == 'dev'
Requires-Dist: ruff>=0.6.9 ; extra == 'dev'
Requires-Dist: ipykernel>=6.29.5 ; extra == 'docs'
Requires-Dist: nbsphinx>=0.9.6 ; extra == 'docs'
Requires-Dist: sphinx>=8.2.3 ; extra == 'docs'
Requires-Dist: sphinx-autodoc-typehints>=2.0 ; extra == 'docs'
Requires-Dist: sphinx-material>=0.0.36 ; extra == 'docs'
Requires-Dist: sphinx-rtd-theme>=2.0 ; extra == 'docs'
Requires-Dist: myst-parser>=4.0 ; extra == 'docs'
Requires-Dist: jupytext>=1.16.7 ; extra == 'docs'
Provides-Extra: dev
Provides-Extra: docs
License-File: LICENSE
License-File: AUTHORS.rst
Summary: A rusty mutex watershed
Author-email: William Patton <wllmpttn24@gmail.com>
Requires-Python: >=3.11
